Metadata-Version: 2.1
Name: comments
Version: 1.0.0
Summary: Python wrapper for the https://comments.bot API
Home-page: https://github.com/AmanoTeam/comments
Author: Amano Team
Author-email: contact@amanoteam.ml
License: UNKNOWN
Platform: UNKNOWN
